universion/__init__.py
universion/cli.py
universion-0.1.2.dist-info/LICENSE.md
universion-0.1.2.dist-info/METADATA
universion-0.1.2.dist-info/WHEEL
universion-0.1.2.dist-info/entry_points.txt
universion-0.1.2.dist-info/top_level.txt
universion-0.1.2.dist-info/RECORD
