Metadata-Version: 2.1
Name: universion
Version: 0.1.2
Summary: An automated versioning tool using semantic versioning and conventional commits that supports a majority of software project types.
Home-page: https://github.com/roblkenn/UniVersion
Author: Robert Kennedy
Author-email: robert076kennedy@gmail.com
License: UNKNOWN
Platform: UNKNOWN
Classifier: Programming Language :: Python :: 3
Classifier: License :: OSI Approved :: MIT License
Classifier: Operating System :: OS Independent
Requires-Dist: Click
Requires-Dist: GitPython
Requires-Dist: setuptools
